__init__.py
lscolumns.py
setup.py
term_size.py
version.py
lscolumns.egg-info/PKG-INFO
lscolumns.egg-info/SOURCES.txt
lscolumns.egg-info/dependency_links.txt
lscolumns.egg-info/top_level.txt