Metadata-Version: 1.0
Name: lscolumns
Version: 0.1.0
Summary: pretty-print columns of data
Home-page: https://github.com/bendmorris/lscolumns
Author: Ben Morris
Author-email: ben@bendmorris.com
License: UNKNOWN
Platform: UNKNOWN
